setup.cfg
setup.py
negative_cycles/__init__.py
negative_cycles/bellman_ford.py
negative_cycles/find_negative_cycle.py
negative_cycles/utils.py
negative_cycles.egg-info/PKG-INFO
negative_cycles.egg-info/SOURCES.txt
negative_cycles.egg-info/dependency_links.txt
negative_cycles.egg-info/requires.txt
negative_cycles.egg-info/top_level.txt
test/test_additive_bellman_ford.py
test/test_negative_cycle_finder.py