Metadata-Version: 1.1
Name: negative-cycles
Version: 0.1.2
Summary: For Negative Cycle Detection
Home-page: https://github.com/mnpatil17/negative_cycles/
Author: Mihir Patil
Author-email: mnpatil17@gmail.com
License: BSD 3-clause "New" or "Revised License"
Keywords: negative-cycle bellman-ford
Platform: UNKNOWN
Classifier: Development Status :: 4 - Beta
Classifier: Intended Audience :: Developers
Classifier: Topic :: Software Development :: Build Tools
Classifier: License :: OSI Approved :: BSD License
Classifier: Programming Language :: Python :: 2.7
